[
  {
    "gid": 10127,
    "consume": 0,
    "reward": 12000,
    "param": 201,
    "time": 1776003650,
    "oid": "69dbaa420fb1d86e44ce4f61-19366830-10127",
    "game_name": "Fire Strike",
    "status": 2,
    "game_name_full": "games-Fire Strike",
    "amount": 12000,
    "type": 1
  },
  {
    "gid": 10127,
    "consume": 600,
    "reward": 0,
    "param": 201,
    "time": 1776003650,
    "oid": "69dbaa417bb2dc002cde53be-19366830-10127",
    "game_name": "Fire Strike",
    "status": 2,
    "game_name_full": "games-Fire Strike",
    "amount": 600,
    "type": 0
  },
  {
    "gid": 10127,
    "consume": 0,
    "reward": 1200,
    "param": 201,
    "time": 1776003646,
    "oid": "69dbaa3e2ee4747801ef4990-19366830-10127",
    "game_name": "Fire Strike",
    "status": 2,
    "game_name_full": "games-Fire Strike",
    "amount": 1200,
    "type": 1
  },
  {
    "gid": 10127,
    "consume": 600,
    "reward": 0,
    "param": 201,
    "time": 1776003646,
    "oid": "69dbaa3e7bb2dc002cde4c21-19366830-10127",
    "game_name": "Fire Strike",
    "status": 2,
    "game_name_full": "games-Fire Strike",
    "amount": 600,
    "type": 0
  },
  {
    "gid": 10127,
    "consume": 0,
    "reward": 4500,
    "param": 201,
    "time": 1776003642,
    "oid": "69dbaa3a2ee4747801ef407a-19366830-10127",
    "game_name": "Fire Strike",
    "status": 2,
    "game_name_full": "games-Fire Strike",
    "amount": 4500,
    "type": 1
  },
  {
    "gid": 10127,
    "consume": 600,
    "reward": 0,
    "param": 201,
    "time": 1776003641,
    "oid": "69dbaa392ee4747801ef3fb2-19366830-10127",
    "game_name": "Fire Strike",
    "status": 2,
    "game_name_full": "games-Fire Strike",
    "amount": 600,
    "type": 0
  },
  {
    "gid": 10127,
    "consume": 600,
    "reward": 0,
    "param": 201,
    "time": 1776003639,
    "oid": "69dbaa372ee4747801ef3bca-19366830-10127",
    "game_name": "Fire Strike",
    "status": 2,
    "game_name_full": "games-Fire Strike",
    "amount": 600,
    "type": 0
  },
  {
    "gid": 10127,
    "consume": 500,
    "reward": 0,
    "param": 201,
    "time": 1776003636,
    "oid": "69dbaa347bb2dc002cde3a2a-19366830-10127",
    "game_name": "Fire Strike",
    "status": 2,
    "game_name_full": "games-Fire Strike",
    "amount": 500,
    "type": 0
  },
  {
    "gid": 10127,
    "consume": 500,
    "reward": 0,
    "param": 201,
    "time": 1776003634,
    "oid": "69dbaa322ee4747801ef3222-19366830-10127",
    "game_name": "Fire Strike",
    "status": 2,
    "game_name_full": "games-Fire Strike",
    "amount": 500,
    "type": 0
  },
  {
    "gid": 10127,
    "consume": 0,
    "reward": 1250,
    "param": 201,
    "time": 1776003630,
    "oid": "69dbaa2e7bb2dc002cde2e35-19366830-10127",
    "game_name": "Fire Strike",
    "status": 2,
    "game_name_full": "games-Fire Strike",
    "amount": 1250,
    "type": 1
  },
  {
    "gid": 10127,
    "consume": 500,
    "reward": 0,
    "param": 201,
    "time": 1776003630,
    "oid": "69dbaa2e2ee4747801ef2909-19366830-10127",
    "game_name": "Fire Strike",
    "status": 2,
    "game_name_full": "games-Fire Strike",
    "amount": 500,
    "type": 0
  },
  {
    "gid": 10127,
    "consume": 500,
    "reward": 0,
    "param": 201,
    "time": 1776003629,
    "oid": "69dbaa2c0fb1d86e44ce256b-19366830-10127",
    "game_name": "Fire Strike",
    "status": 2,
    "game_name_full": "games-Fire Strike",
    "amount": 500,
    "type": 0
  },
  {
    "gid": 10127,
    "consume": 500,
    "reward": 0,
    "param": 201,
    "time": 1776003627,
    "oid": "69dbaa2a0fb1d86e44ce2152-19366830-10127",
    "game_name": "Fire Strike",
    "status": 2,
    "game_name_full": "games-Fire Strike",
    "amount": 500,
    "type": 0
  },
  {
    "gid": 10127,
    "consume": 500,
    "reward": 0,
    "param": 201,
    "time": 1776003625,
    "oid": "69dbaa287bb2dc002cde234c-19366830-10127",
    "game_name": "Fire Strike",
    "status": 2,
    "game_name_full": "games-Fire Strike",
    "amount": 500,
    "type": 0
  },
  {
    "gid": 10127,
    "consume": 0,
    "reward": 750,
    "param": 201,
    "time": 1776003622,
    "oid": "69dbaa260fb1d86e44ce181e-19366830-10127",
    "game_name": "Fire Strike",
    "status": 2,
    "game_name_full": "games-Fire Strike",
    "amount": 750,
    "type": 1
  },
  {
    "gid": 10127,
    "consume": 500,
    "reward": 0,
    "param": 201,
    "time": 1776003621,
    "oid": "69dbaa257bb2dc002cde1c1d-19366830-10127",
    "game_name": "Fire Strike",
    "status": 2,
    "game_name_full": "games-Fire Strike",
    "amount": 500,
    "type": 0
  },
  {
    "gid": 10127,
    "consume": 0,
    "reward": 1250,
    "param": 201,
    "time": 1776003618,
    "oid": "69dbaa222ee4747801ef10c1-19366830-10127",
    "game_name": "Fire Strike",
    "status": 2,
    "game_name_full": "games-Fire Strike",
    "amount": 1250,
    "type": 1
  },
  {
    "gid": 10127,
    "consume": 500,
    "reward": 0,
    "param": 201,
    "time": 1776003617,
    "oid": "69dbaa210fb1d86e44ce0ebd-19366830-10127",
    "game_name": "Fire Strike",
    "status": 2,
    "game_name_full": "games-Fire Strike",
    "amount": 500,
    "type": 0
  },
  {
    "gid": 10127,
    "consume": 0,
    "reward": 750,
    "param": 201,
    "time": 1776003615,
    "oid": "69dbaa1f2ee4747801ef0b7a-19366830-10127",
    "game_name": "Fire Strike",
    "status": 2,
    "game_name_full": "games-Fire Strike",
    "amount": 750,
    "type": 1
  },
  {
    "gid": 10127,
    "consume": 500,
    "reward": 0,
    "param": 201,
    "time": 1776003614,
    "oid": "69dbaa1e0fb1d86e44ce09a0-19366830-10127",
    "game_name": "Fire Strike",
    "status": 2,
    "game_name_full": "games-Fire Strike",
    "amount": 500,
    "type": 0
  }
]